plesk_sdk/__init__.py
plesk_sdk/client.py
plesk_sdk/patterns.py
plesk_sdk/responses.py
plesk_sdk-0.2.2.dist-info/WHEEL
plesk_sdk-0.2.2.dist-info/METADATA
plesk_sdk-0.2.2.dist-info/RECORD
